xsnap/__init__.py
xsnap/_fitting.py
xsnap/analysis.py
xsnap/detect.py
xsnap/make_region.py
xsnap/spectrum.py
xsnap/temperature.py
xsnap/chandra/extract.py
xsnap/nustar/extract.py
xsnap/swiftxrt/extract.py
xsnap/swiftxrt/stack_pc.py
xsnap/xmm/extract.py
xsnap-0.2.6.dist-info/licenses/LICENSE
xsnap-0.2.6.dist-info/METADATA
xsnap-0.2.6.dist-info/WHEEL
xsnap-0.2.6.dist-info/entry_points.txt
xsnap-0.2.6.dist-info/top_level.txt
xsnap-0.2.6.dist-info/RECORD
