Metadata-Version: 2.4
Name: xsnap
Version: 0.2.6
Summary: A Python-based pipeline module to easily handle data calibration from Chandra, Swift-XRT, XMM-Newton, and NuSTAR data. Additionally, spectral fitting and analysis are available with the help of XSPEC
Author-email: Ferdinand <support@xsnap.org>
Maintainer-email: Ferdinand <support@xsnap.org>
License: MIT License
Project-URL: Homepage, https://xsnap.org/
Project-URL: Repository, https://github.com/fercananything/XSNAP/
Project-URL: Issues, https://github.com/fercananything/XSNAP/issues
Project-URL: Changelog, https://github.com/fercananything/XSNAP/blob/main/CHANGELOG.md
Keywords: astronomy,xray,spectroscopy,pipeline,supernova
Classifier: Development Status :: 4 - Beta
Classifier: Intended Audience :: Science/Research
Classifier: License :: OSI Approved :: MIT License
Classifier: Programming Language :: Python :: 3.12
Classifier: Topic :: Scientific/Engineering :: Astronomy
Classifier: Topic :: Scientific/Engineering :: Physics
Requires-Python: >=3.12
License-File: LICENSE
Requires-Dist: astropy>=7.0.0
Requires-Dist: corner>=2.2.2
Requires-Dist: emcee>=3.1.6
Requires-Dist: matplotlib>=3.10.3
Requires-Dist: numpy<2.0.0
Requires-Dist: pandas>=2.2.3
Requires-Dist: scipy>=1.15.1
Dynamic: license-file
